{
  "name": "Rebecca Hubbard",
  "age": 55,
  "address": {
    "street": "Rizfu Court",
    "city": "Iweedfow",
    "state": "ND",
    "zip": "16144"
  },
  "contact": {
    "phone": "(663) 852-2525",
    "servicePhone": "800956643"
  },
  "birthday": "1984-12-27T01:01:17.948Z",
  "ip": "109.215.62.172",
  "foo": "bar",
  "profile": {
    "about": "No soza uleje uza re huj uvu cistenkod bocsar racheof ube aho oz ba beca ek po. Dudrov zezohuz niub cumema zuesoko gifmib afebopdo kanlizup uticocar ja vafgo bechu fe wogorkow ohbihu ser. Imovikuhu ge mifwod jezom sisi kohi iwegigmar zufof lem isa pana wuzjir hav web hoikavoz igu haj. Jinvuse juf fi wioj hap bude gehuvjup peduivi amonahig gifevdag deldu macgovu ucacu lot tuwtir min idozekos. Fosse zazal givhur cusdudte vozo puvildu perfi ditisu boffacsu uh lin agzibote.",
    "bio": "Mubnit sum pualu famevuwik eri soaf bitvuzo covhu ir gis wul jeikfom. Vih uw suuwe daihro or tisdu jewob buspuwva zug inipij ezla ten cof wilolew hepeloso net ta. Bor obanirba bokif kecdektis gehiv feunalus ohuja oru ijupiftul buksu pudwe upanuge med in uwar odav. Secesu ge ikduc jon ra fabos muad deoraub tufgowfum cuvconul losa re zenol woiro cadevbil. Jiplomtu vobudode hu hag efehunu powo ji dus icpumu ceogwup kicwicjaf gemma udsigen vodrola."
  },
  "apiKey": "f99d1ab0f7f064abb37d6d147a87110ed7404fc466c7901a252fd96f555618cb",
  "currency": {
    "code": "JOD",
    "name": "Jordan Dinar"
  }
}